{
  "crops": {
    "rows": [
      {
        "name": "Wheat",
        "variety": "Winter Wheat",
        "field": "Field A",
        "area_hectares": 25.5,
        "planting_date": "2025-10-15",
        "expected_harvest": "2026-06-20",
        "status": "growing",
        "yield_kg": null,
        "notes": "Main grain crop",
        "id": 1,
        "created_at": "2026-05-10 03:46:54"
      },
      {
        "name": "Corn",
        "variety": "Sweet Corn",
        "field": "Field B",
        "area_hectares": 18,
        "planting_date": "2025-04-10",
        "expected_harvest": "2025-08-30",
        "status": "harvested",
        "yield_kg": 8200,
        "notes": "Excellent yield",
        "id": 2,
        "created_at": "2026-05-10 03:46:54"
      },
      {
        "name": "Soybeans",
        "variety": "Glyphosate-Resistant",
        "field": "Field C",
        "area_hectares": 30,
        "planting_date": "2025-05-01",
        "expected_harvest": "2025-10-15",
        "status": "harvested",
        "yield_kg": 5400,
        "notes": "Good season",
        "id": 3,
        "created_at": "2026-05-10 03:46:54"
      },
      {
        "name": "Tomatoes",
        "variety": "Roma",
        "field": "Greenhouse 1",
        "area_hectares": 2.5,
        "planting_date": "2026-02-01",
        "expected_harvest": "2026-05-15",
        "status": "growing",
        "yield_kg": null,
        "notes": "Drip irrigation",
        "id": 4,
        "created_at": "2026-05-10 03:46:54"
      },
      {
        "name": "Sunflowers",
        "variety": "Hybrid",
        "field": "Field D",
        "area_hectares": 12,
        "planting_date": "2026-04-20",
        "expected_harvest": "2026-09-01",
        "status": "planned",
        "yield_kg": null,
        "notes": "Oil production",
        "id": 5,
        "created_at": "2026-05-10 03:46:54"
      },
      {
        "name": "Rice",
        "variety": "Jasmine",
        "field": "Field E",
        "area_hectares": 20,
        "planting_date": "2026-05-01",
        "expected_harvest": "2026-10-30",
        "status": "growing",
        "yield_kg": null,
        "notes": "Paddy field",
        "id": 6,
        "created_at": "2026-05-10 03:46:54"
      },
      {
        "name": "carot",
        "variety": "mera",
        "field": "hjhgf",
        "area_hectares": "ugand",
        "planting_date": "2026-05-11",
        "expected_harvest": "2026-05-07",
        "status": "harvested",
        "yield_kg": "2133",
        "notes": null,
        "actual_harvest": "2026-04-30",
        "id": 7,
        "created_at": "2026-05-10 21:39:35"
      }
    ],
    "seq": 7
  },
  "livestock": {
    "rows": [
      {
        "tag_id": "COW-001",
        "type": "Cattle",
        "breed": "Holstein",
        "gender": "Female",
        "birth_date": "2022-03-15",
        "weight_kg": 580,
        "health_status": "healthy",
        "location": "Barn A",
        "id": 1,
        "created_at": "2026-05-10 03:46:54"
      },
      {
        "tag_id": "COW-002",
        "type": "Cattle",
        "breed": "Angus",
        "gender": "Male",
        "birth_date": "2021-07-20",
        "weight_kg": 720,
        "health_status": "healthy",
        "location": "Pasture 1",
        "id": 2,
        "created_at": "2026-05-10 03:46:54"
      },
      {
        "tag_id": "COW-003",
        "type": "Cattle",
        "breed": "Jersey",
        "gender": "Female",
        "birth_date": "2023-01-10",
        "weight_kg": 450,
        "health_status": "healthy",
        "location": "Barn A",
        "id": 3,
        "created_at": "2026-05-10 03:46:54"
      },
      {
        "tag_id": "SHP-001",
        "type": "Sheep",
        "breed": "Merino",
        "gender": "Female",
        "birth_date": "2023-05-05",
        "weight_kg": 65,
        "health_status": "healthy",
        "location": "Pasture 2",
        "id": 4,
        "created_at": "2026-05-10 03:46:54"
      },
      {
        "tag_id": "SHP-002",
        "type": "Sheep",
        "breed": "Suffolk",
        "gender": "Male",
        "birth_date": "2022-11-18",
        "weight_kg": 85,
        "health_status": "under_treatment",
        "location": "Quarantine",
        "id": 5,
        "created_at": "2026-05-10 03:46:54"
      },
      {
        "tag_id": "PIG-001",
        "type": "Pig",
        "breed": "Duroc",
        "gender": "Female",
        "birth_date": "2024-01-20",
        "weight_kg": 120,
        "health_status": "healthy",
        "location": "Pig House",
        "id": 6,
        "created_at": "2026-05-10 03:46:54"
      },
      {
        "tag_id": "CHK-001",
        "type": "Chicken",
        "breed": "Broiler",
        "gender": "Female",
        "birth_date": "2025-09-01",
        "weight_kg": 2.8,
        "health_status": "healthy",
        "location": "Poultry House",
        "id": 7,
        "created_at": "2026-05-10 03:46:54"
      },
      {
        "tag_id": "CHK-002",
        "type": "Chicken",
        "breed": "Layer",
        "gender": "Female",
        "birth_date": "2025-06-15",
        "weight_kg": 1.9,
        "health_status": "healthy",
        "location": "Poultry House",
        "id": 8,
        "created_at": "2026-05-10 03:46:54"
      },
      {
        "tag_id": "GOT-001",
        "type": "Goat",
        "breed": "Boer",
        "gender": "Male",
        "birth_date": "2023-08-12",
        "weight_kg": 75,
        "health_status": "healthy",
        "location": "Pasture 3",
        "id": 9,
        "created_at": "2026-05-10 03:46:54"
      }
    ],
    "seq": 9
  },
  "inventory": {
    "rows": [
      {
        "name": "Wheat Seeds",
        "category": "Seeds",
        "quantity": 500,
        "unit": "kg",
        "unit_price": 2.5,
        "supplier": "AgriSupply Co",
        "location": "Warehouse A",
        "min_quantity": 100,
        "id": 1,
        "created_at": "2026-05-10 03:46:54"
      },
      {
        "name": "NPK Fertilizer",
        "category": "Fertilizer",
        "quantity": 1200,
        "unit": "kg",
        "unit_price": 1.8,
        "supplier": "FertileCrop Ltd",
        "location": "Warehouse B",
        "min_quantity": 200,
        "id": 2,
        "created_at": "2026-05-10 03:46:54"
      },
      {
        "name": "Herbicide X",
        "category": "Pesticide",
        "quantity": 80,
        "unit": "L",
        "unit_price": 15,
        "supplier": "CropProtect",
        "location": "Chemical Store",
        "min_quantity": 20,
        "id": 3,
        "created_at": "2026-05-10 03:46:54"
      },
      {
        "name": "Diesel Fuel",
        "category": "Fuel",
        "quantity": 3000,
        "unit": "L",
        "unit_price": 1.2,
        "supplier": "FuelMart",
        "location": "Fuel Tank",
        "min_quantity": 500,
        "id": 4,
        "created_at": "2026-05-10 03:46:54"
      },
      {
        "name": "Irrigation Pipes",
        "category": "Equipment",
        "quantity": 200,
        "unit": "m",
        "unit_price": 3.5,
        "supplier": "IrriTech",
        "location": "Workshop",
        "min_quantity": 50,
        "id": 5,
        "created_at": "2026-05-10 03:46:54"
      },
      {
        "name": "Corn Seeds",
        "category": "Seeds",
        "quantity": 300,
        "unit": "kg",
        "unit_price": 3.2,
        "supplier": "AgriSupply Co",
        "location": "Warehouse A",
        "min_quantity": 80,
        "id": 6,
        "created_at": "2026-05-10 03:46:54"
      },
      {
        "name": "Lime",
        "category": "Soil Amendment",
        "quantity": 800,
        "unit": "kg",
        "unit_price": 0.9,
        "supplier": "SoilCo",
        "location": "Warehouse B",
        "min_quantity": 150,
        "id": 7,
        "created_at": "2026-05-10 03:46:54"
      },
      {
        "name": "Insecticide Y",
        "category": "Pesticide",
        "quantity": 45,
        "unit": "L",
        "unit_price": 18,
        "supplier": "CropProtect",
        "location": "Chemical Store",
        "min_quantity": 10,
        "id": 8,
        "created_at": "2026-05-10 03:46:54"
      },
      {
        "name": "Hay Bales",
        "category": "Feed",
        "quantity": 150,
        "unit": "bale",
        "unit_price": 12,
        "supplier": "LocalFarm",
        "location": "Feed Store",
        "min_quantity": 30,
        "id": 9,
        "created_at": "2026-05-10 03:46:54"
      },
      {
        "name": "Vitamin Supplement",
        "category": "Feed Additive",
        "quantity": 25,
        "unit": "kg",
        "unit_price": 35,
        "supplier": "VetSupply",
        "location": "Feed Store",
        "min_quantity": 5,
        "id": 10,
        "created_at": "2026-05-10 03:46:54"
      }
    ],
    "seq": 10
  },
  "transactions": {
    "rows": [
      {
        "type": "income",
        "category": "Crop Sales",
        "amount": 45000,
        "date": "2026-01-15",
        "description": "Wheat harvest sale",
        "payment_method": "bank_transfer",
        "id": 1,
        "created_at": "2026-05-10 03:46:54"
      },
      {
        "type": "income",
        "category": "Livestock Sales",
        "amount": 12000,
        "date": "2026-01-28",
        "description": "Cattle sale",
        "payment_method": "bank_transfer",
        "id": 2,
        "created_at": "2026-05-10 03:46:54"
      },
      {
        "type": "expense",
        "category": "Fertilizer",
        "amount": 3200,
        "date": "2026-02-05",
        "description": "NPK purchase Q1",
        "payment_method": "cash",
        "id": 3,
        "created_at": "2026-05-10 03:46:54"
      },
      {
        "type": "expense",
        "category": "Labor",
        "amount": 8500,
        "date": "2026-02-28",
        "description": "Monthly wages",
        "payment_method": "bank_transfer",
        "id": 4,
        "created_at": "2026-05-10 03:46:54"
      },
      {
        "type": "income",
        "category": "Crop Sales",
        "amount": 28000,
        "date": "2026-03-10",
        "description": "Corn sale",
        "payment_method": "bank_transfer",
        "id": 5,
        "created_at": "2026-05-10 03:46:54"
      },
      {
        "type": "expense",
        "category": "Equipment Maintenance",
        "amount": 1500,
        "date": "2026-03-20",
        "description": "Tractor service",
        "payment_method": "cash",
        "id": 6,
        "created_at": "2026-05-10 03:46:54"
      },
      {
        "type": "expense",
        "category": "Seeds",
        "amount": 2800,
        "date": "2026-04-01",
        "description": "Spring planting seeds",
        "payment_method": "bank_transfer",
        "id": 7,
        "created_at": "2026-05-10 03:46:54"
      },
      {
        "type": "income",
        "category": "Dairy Products",
        "amount": 6000,
        "date": "2026-04-15",
        "description": "Milk sales",
        "payment_method": "bank_transfer",
        "id": 8,
        "created_at": "2026-05-10 03:46:54"
      },
      {
        "type": "expense",
        "category": "Fuel",
        "amount": 1800,
        "date": "2026-04-30",
        "description": "Monthly fuel cost",
        "payment_method": "cash",
        "id": 9,
        "created_at": "2026-05-10 03:46:54"
      },
      {
        "type": "income",
        "category": "Livestock Sales",
        "amount": 9500,
        "date": "2026-05-05",
        "description": "Pig sale",
        "payment_method": "bank_transfer",
        "id": 10,
        "created_at": "2026-05-10 03:46:54"
      },
      {
        "type": "expense",
        "category": "Labor",
        "amount": 8500,
        "date": "2026-05-01",
        "description": "Monthly wages",
        "payment_method": "bank_transfer",
        "id": 11,
        "created_at": "2026-05-10 03:46:54"
      },
      {
        "type": "income",
        "category": "Crop Sales",
        "amount": 15000,
        "date": "2026-05-08",
        "description": "Soybean sale",
        "payment_method": "bank_transfer",
        "id": 12,
        "created_at": "2026-05-10 03:46:54"
      }
    ],
    "seq": 12
  },
  "workers": {
    "rows": [
      {
        "name": "James Mwangi",
        "role": "Farm Manager",
        "phone": "0712-345-678",
        "email": "james@farm.com",
        "hire_date": "2020-03-01",
        "salary": 85000,
        "status": "active",
        "department": "Management",
        "id": 1,
        "created_at": "2026-05-10 03:46:54"
      },
      {
        "name": "Fatuma Ochieng",
        "role": "Agronomist",
        "phone": "0723-456-789",
        "email": "fatuma@farm.com",
        "hire_date": "2021-06-15",
        "salary": 65000,
        "status": "active",
        "department": "Agronomy",
        "id": 2,
        "created_at": "2026-05-10 03:46:54"
      },
      {
        "name": "Peter Kamau",
        "role": "Livestock Supervisor",
        "phone": "0734-567-890",
        "email": "peter@farm.com",
        "hire_date": "2019-11-01",
        "salary": 55000,
        "status": "active",
        "department": "Livestock",
        "id": 3,
        "created_at": "2026-05-10 03:46:54"
      },
      {
        "name": "Grace Wanjiku",
        "role": "Finance Officer",
        "phone": "0745-678-901",
        "email": "grace@farm.com",
        "hire_date": "2022-01-10",
        "salary": 60000,
        "status": "active",
        "department": "Finance",
        "id": 4,
        "created_at": "2026-05-10 03:46:54"
      },
      {
        "name": "David Otieno",
        "role": "Equipment Operator",
        "phone": "0756-789-012",
        "email": "david@farm.com",
        "hire_date": "2021-08-20",
        "salary": 42000,
        "status": "active",
        "department": "Operations",
        "id": 5,
        "created_at": "2026-05-10 03:46:54"
      },
      {
        "name": "Mary Njeri",
        "role": "Field Supervisor",
        "phone": "0767-890-123",
        "email": "mary@farm.com",
        "hire_date": "2020-05-15",
        "salary": 48000,
        "status": "active",
        "department": "Operations",
        "id": 6,
        "created_at": "2026-05-10 03:46:54"
      },
      {
        "name": "Samuel Kibet",
        "role": "Irrigation Technician",
        "phone": "0778-901-234",
        "email": "samuel@farm.com",
        "hire_date": "2023-02-01",
        "salary": 40000,
        "status": "active",
        "department": "Operations",
        "id": 7,
        "created_at": "2026-05-10 03:46:54"
      },
      {
        "name": "Aisha Hassan",
        "role": "Accountant",
        "phone": "0789-012-345",
        "email": "aisha@farm.com",
        "hire_date": "2022-09-01",
        "salary": 55000,
        "status": "on_leave",
        "department": "Finance",
        "id": 8,
        "created_at": "2026-05-10 03:46:54"
      }
    ],
    "seq": 8
  },
  "equipment": {
    "rows": [
      {
        "name": "John Deere 6M",
        "type": "Tractor",
        "model": "6130M",
        "serial_number": "JD6M-2021-001",
        "purchase_date": "2021-03-15",
        "purchase_price": 4500000,
        "status": "operational",
        "last_maintenance": "2026-03-01",
        "next_maintenance": "2026-09-01",
        "location": "Equipment Yard",
        "id": 1,
        "created_at": "2026-05-10 03:46:54"
      },
      {
        "name": "New Holland T5",
        "type": "Tractor",
        "model": "T5.120",
        "serial_number": "NH5-2020-002",
        "purchase_date": "2020-07-20",
        "purchase_price": 3800000,
        "status": "operational",
        "last_maintenance": "2026-04-15",
        "next_maintenance": "2026-10-15",
        "location": "Field B",
        "id": 2,
        "created_at": "2026-05-10 03:46:54"
      },
      {
        "name": "Combine Harvester",
        "type": "Harvester",
        "model": "Claas Lexion 750",
        "serial_number": "CL750-2022-001",
        "purchase_date": "2022-01-10",
        "purchase_price": 12000000,
        "status": "operational",
        "last_maintenance": "2025-12-01",
        "next_maintenance": "2026-06-01",
        "location": "Equipment Yard",
        "id": 3,
        "created_at": "2026-05-10 03:46:54"
      },
      {
        "name": "Irrigation Pump",
        "type": "Pump",
        "model": "Grundfos CM5",
        "serial_number": "GF-2021-003",
        "purchase_date": "2021-05-01",
        "purchase_price": 180000,
        "status": "operational",
        "last_maintenance": "2026-02-01",
        "next_maintenance": "2026-08-01",
        "location": "Field A",
        "id": 4,
        "created_at": "2026-05-10 03:46:54"
      },
      {
        "name": "Sprayer",
        "type": "Sprayer",
        "model": "AGCO 4200",
        "serial_number": "AG4200-2023-001",
        "purchase_date": "2023-08-15",
        "purchase_price": 650000,
        "status": "operational",
        "last_maintenance": "2026-01-15",
        "next_maintenance": "2026-07-15",
        "location": "Equipment Yard",
        "id": 5,
        "created_at": "2026-05-10 03:46:54"
      },
      {
        "name": "Seed Drill",
        "type": "Planter",
        "model": "Horsch Maestro",
        "serial_number": "HM-2022-002",
        "purchase_date": "2022-11-20",
        "purchase_price": 950000,
        "status": "under_maintenance",
        "last_maintenance": "2026-05-01",
        "next_maintenance": "2026-05-30",
        "location": "Workshop",
        "id": 6,
        "created_at": "2026-05-10 03:46:54"
      },
      {
        "name": "Grain Dryer",
        "type": "Dryer",
        "model": "Sukup 2410",
        "serial_number": "SK2410-2020-001",
        "purchase_date": "2020-09-10",
        "purchase_price": 1200000,
        "status": "operational",
        "last_maintenance": "2025-11-01",
        "next_maintenance": "2026-05-01",
        "location": "Warehouse A",
        "id": 7,
        "created_at": "2026-05-10 03:46:54"
      },
      {
        "name": "Pickup Truck",
        "type": "Vehicle",
        "model": "Toyota Hilux",
        "serial_number": "TH-2023-003",
        "purchase_date": "2023-04-01",
        "purchase_price": 2800000,
        "status": "operational",
        "last_maintenance": "2026-04-01",
        "next_maintenance": "2026-10-01",
        "location": "Farm Office",
        "id": 8,
        "created_at": "2026-05-10 03:46:54"
      }
    ],
    "seq": 8
  },
  "sales": {
    "rows": [
      {
        "product": "Wheat",
        "customer": "Nairobi Millers Ltd",
        "quantity": 20000,
        "unit": "kg",
        "unit_price": 22.5,
        "total_amount": 450000,
        "date": "2026-01-15",
        "status": "completed",
        "payment_method": "bank_transfer",
        "id": 1,
        "created_at": "2026-05-10 03:46:54"
      },
      {
        "product": "Cattle (5 head)",
        "customer": "Local Butcher",
        "quantity": 5,
        "unit": "head",
        "unit_price": 65000,
        "total_amount": 325000,
        "date": "2026-01-28",
        "status": "completed",
        "payment_method": "bank_transfer",
        "id": 2,
        "created_at": "2026-05-10 03:46:54"
      },
      {
        "product": "Corn",
        "customer": "Feed & Grain Co",
        "quantity": 14000,
        "unit": "kg",
        "unit_price": 20,
        "total_amount": 280000,
        "date": "2026-03-10",
        "status": "completed",
        "payment_method": "bank_transfer",
        "id": 3,
        "created_at": "2026-05-10 03:46:54"
      },
      {
        "product": "Fresh Milk",
        "customer": "Dairy Cooperative",
        "quantity": 3000,
        "unit": "L",
        "unit_price": 60,
        "total_amount": 180000,
        "date": "2026-04-15",
        "status": "completed",
        "payment_method": "bank_transfer",
        "id": 4,
        "created_at": "2026-05-10 03:46:54"
      },
      {
        "product": "Pig (6 head)",
        "customer": "Meat Processor",
        "quantity": 6,
        "unit": "head",
        "unit_price": 25000,
        "total_amount": 150000,
        "date": "2026-05-05",
        "status": "completed",
        "payment_method": "cash",
        "id": 5,
        "created_at": "2026-05-10 03:46:54"
      },
      {
        "product": "Soybeans",
        "customer": "Oil Processor",
        "quantity": 8000,
        "unit": "kg",
        "unit_price": 45,
        "total_amount": 360000,
        "date": "2026-05-08",
        "status": "completed",
        "payment_method": "bank_transfer",
        "id": 6,
        "created_at": "2026-05-10 03:46:54"
      },
      {
        "product": "Tomatoes",
        "customer": "City Market",
        "quantity": 500,
        "unit": "kg",
        "unit_price": 80,
        "total_amount": 40000,
        "date": "2026-05-09",
        "status": "pending",
        "payment_method": "cash",
        "id": 7,
        "created_at": "2026-05-10 03:46:54"
      }
    ],
    "seq": 7
  },
  "attendance": {
    "rows": [
      {
        "worker_id": 1,
        "worker_name": "James Mwangi",
        "date": "2026-05-05",
        "clock_in": "07:26",
        "clock_out": "17:30",
        "status": "present",
        "hours_worked": 10,
        "overtime_hours": 2,
        "location": "Farm Office",
        "photo_verified": true,
        "notes": null,
        "id": 1,
        "created_at": "2026-05-10 04:09:00"
      },
      {
        "worker_id": 2,
        "worker_name": "Fatuma Ochieng",
        "date": "2026-05-05",
        "clock_in": "07:00",
        "clock_out": "17:30",
        "status": "present",
        "hours_worked": 10,
        "overtime_hours": 2,
        "location": "Field A",
        "photo_verified": true,
        "notes": null,
        "id": 2,
        "created_at": "2026-05-10 04:09:00"
      },
      {
        "worker_id": 3,
        "worker_name": "Peter Kamau",
        "date": "2026-05-05",
        "clock_in": "07:04",
        "clock_out": "17:30",
        "status": "present",
        "hours_worked": 10,
        "overtime_hours": 2,
        "location": "Barn A",
        "photo_verified": true,
        "notes": null,
        "id": 3,
        "created_at": "2026-05-10 04:09:00"
      },
      {
        "worker_id": 4,
        "worker_name": "Grace Wanjiku",
        "date": "2026-05-05",
        "clock_in": null,
        "clock_out": null,
        "status": "on_leave",
        "hours_worked": 0,
        "overtime_hours": 0,
        "location": null,
        "photo_verified": false,
        "notes": null,
        "id": 4,
        "created_at": "2026-05-10 04:09:00"
      },
      {
        "worker_id": 5,
        "worker_name": "David Otieno",
        "date": "2026-05-05",
        "clock_in": "07:12",
        "clock_out": "17:30",
        "status": "present",
        "hours_worked": 10,
        "overtime_hours": 2,
        "location": "Field D",
        "photo_verified": true,
        "notes": null,
        "id": 5,
        "created_at": "2026-05-10 04:09:00"
      },
      {
        "worker_id": 6,
        "worker_name": "Mary Njeri",
        "date": "2026-05-05",
        "clock_in": "07:16",
        "clock_out": "17:30",
        "status": "present",
        "hours_worked": 10,
        "overtime_hours": 2,
        "location": "Field C",
        "photo_verified": true,
        "notes": null,
        "id": 6,
        "created_at": "2026-05-10 04:09:00"
      },
      {
        "worker_id": 7,
        "worker_name": "Samuel Kibet",
        "date": "2026-05-05",
        "clock_in": "07:20",
        "clock_out": "17:30",
        "status": "present",
        "hours_worked": 10,
        "overtime_hours": 2,
        "location": "Field E",
        "photo_verified": true,
        "notes": null,
        "id": 7,
        "created_at": "2026-05-10 04:09:00"
      },
      {
        "worker_id": 8,
        "worker_name": "Aisha Hassan",
        "date": "2026-05-05",
        "clock_in": null,
        "clock_out": null,
        "status": "on_leave",
        "hours_worked": 0,
        "overtime_hours": 0,
        "location": null,
        "photo_verified": false,
        "notes": null,
        "id": 8,
        "created_at": "2026-05-10 04:09:00"
      },
      {
        "worker_id": 1,
        "worker_name": "James Mwangi",
        "date": "2026-05-06",
        "clock_in": "07:26",
        "clock_out": "17:30",
        "status": "present",
        "hours_worked": 10,
        "overtime_hours": 2,
        "location": "Farm Office",
        "photo_verified": true,
        "notes": null,
        "id": 9,
        "created_at": "2026-05-10 04:09:00"
      },
      {
        "worker_id": 2,
        "worker_name": "Fatuma Ochieng",
        "date": "2026-05-06",
        "clock_in": "08:35",
        "clock_out": "17:15",
        "status": "late",
        "hours_worked": 8.67,
        "overtime_hours": 0.67,
        "location": "Field A",
        "photo_verified": true,
        "notes": "Late arrival at 08:35",
        "id": 10,
        "created_at": "2026-05-10 04:09:00"
      },
      {
        "worker_id": 3,
        "worker_name": "Peter Kamau",
        "date": "2026-05-06",
        "clock_in": "07:04",
        "clock_out": "17:30",
        "status": "present",
        "hours_worked": 10,
        "overtime_hours": 2,
        "location": "Barn A",
        "photo_verified": true,
        "notes": null,
        "id": 11,
        "created_at": "2026-05-10 04:09:00"
      },
      {
        "worker_id": 4,
        "worker_name": "Grace Wanjiku",
        "date": "2026-05-06",
        "clock_in": null,
        "clock_out": null,
        "status": "on_leave",
        "hours_worked": 0,
        "overtime_hours": 0,
        "location": null,
        "photo_verified": false,
        "notes": null,
        "id": 12,
        "created_at": "2026-05-10 04:09:00"
      },
      {
        "worker_id": 5,
        "worker_name": "David Otieno",
        "date": "2026-05-06",
        "clock_in": "08:35",
        "clock_out": "17:15",
        "status": "late",
        "hours_worked": 8.67,
        "overtime_hours": 0.67,
        "location": "Field D",
        "photo_verified": true,
        "notes": "Late arrival at 08:35",
        "id": 13,
        "created_at": "2026-05-10 04:09:00"
      },
      {
        "worker_id": 6,
        "worker_name": "Mary Njeri",
        "date": "2026-05-06",
        "clock_in": "07:16",
        "clock_out": "17:30",
        "status": "present",
        "hours_worked": 10,
        "overtime_hours": 2,
        "location": "Field C",
        "photo_verified": true,
        "notes": null,
        "id": 14,
        "created_at": "2026-05-10 04:09:00"
      },
      {
        "worker_id": 7,
        "worker_name": "Samuel Kibet",
        "date": "2026-05-06",
        "clock_in": "07:20",
        "clock_out": "17:30",
        "status": "present",
        "hours_worked": 10,
        "overtime_hours": 2,
        "location": "Field E",
        "photo_verified": true,
        "notes": null,
        "id": 15,
        "created_at": "2026-05-10 04:09:00"
      },
      {
        "worker_id": 8,
        "worker_name": "Aisha Hassan",
        "date": "2026-05-06",
        "clock_in": null,
        "clock_out": null,
        "status": "on_leave",
        "hours_worked": 0,
        "overtime_hours": 0,
        "location": null,
        "photo_verified": false,
        "notes": null,
        "id": 16,
        "created_at": "2026-05-10 04:09:00"
      },
      {
        "worker_id": 1,
        "worker_name": "James Mwangi",
        "date": "2026-05-07",
        "clock_in": "07:26",
        "clock_out": "17:30",
        "status": "present",
        "hours_worked": 10,
        "overtime_hours": 2,
        "location": "Farm Office",
        "photo_verified": true,
        "notes": null,
        "id": 17,
        "created_at": "2026-05-10 04:09:00"
      },
      {
        "worker_id": 2,
        "worker_name": "Fatuma Ochieng",
        "date": "2026-05-07",
        "clock_in": "07:00",
        "clock_out": "17:30",
        "status": "present",
        "hours_worked": 10,
        "overtime_hours": 2,
        "location": "Field A",
        "photo_verified": true,
        "notes": null,
        "id": 18,
        "created_at": "2026-05-10 04:09:00"
      },
      {
        "worker_id": 3,
        "worker_name": "Peter Kamau",
        "date": "2026-05-07",
        "clock_in": "07:04",
        "clock_out": "17:30",
        "status": "present",
        "hours_worked": 10,
        "overtime_hours": 2,
        "location": "Barn A",
        "photo_verified": true,
        "notes": null,
        "id": 19,
        "created_at": "2026-05-10 04:09:00"
      },
      {
        "worker_id": 4,
        "worker_name": "Grace Wanjiku",
        "date": "2026-05-07",
        "clock_in": null,
        "clock_out": null,
        "status": "on_leave",
        "hours_worked": 0,
        "overtime_hours": 0,
        "location": null,
        "photo_verified": false,
        "notes": null,
        "id": 20,
        "created_at": "2026-05-10 04:09:00"
      },
      {
        "worker_id": 5,
        "worker_name": "David Otieno",
        "date": "2026-05-07",
        "clock_in": "07:12",
        "clock_out": "17:30",
        "status": "present",
        "hours_worked": 10,
        "overtime_hours": 2,
        "location": "Field D",
        "photo_verified": true,
        "notes": null,
        "id": 21,
        "created_at": "2026-05-10 04:09:00"
      },
      {
        "worker_id": 6,
        "worker_name": "Mary Njeri",
        "date": "2026-05-07",
        "clock_in": "07:16",
        "clock_out": "17:30",
        "status": "present",
        "hours_worked": 10,
        "overtime_hours": 2,
        "location": "Field C",
        "photo_verified": true,
        "notes": null,
        "id": 22,
        "created_at": "2026-05-10 04:09:00"
      },
      {
        "worker_id": 7,
        "worker_name": "Samuel Kibet",
        "date": "2026-05-07",
        "clock_in": null,
        "clock_out": null,
        "status": "absent",
        "hours_worked": 0,
        "overtime_hours": 0,
        "location": "Field E",
        "photo_verified": false,
        "notes": null,
        "id": 23,
        "created_at": "2026-05-10 04:09:00"
      },
      {
        "worker_id": 8,
        "worker_name": "Aisha Hassan",
        "date": "2026-05-07",
        "clock_in": null,
        "clock_out": null,
        "status": "on_leave",
        "hours_worked": 0,
        "overtime_hours": 0,
        "location": null,
        "photo_verified": false,
        "notes": null,
        "id": 24,
        "created_at": "2026-05-10 04:09:00"
      },
      {
        "worker_id": 1,
        "worker_name": "James Mwangi",
        "date": "2026-05-08",
        "clock_in": "07:26",
        "clock_out": "17:30",
        "status": "present",
        "hours_worked": 10,
        "overtime_hours": 2,
        "location": "Farm Office",
        "photo_verified": true,
        "notes": null,
        "id": 25,
        "created_at": "2026-05-10 04:09:00"
      },
      {
        "worker_id": 2,
        "worker_name": "Fatuma Ochieng",
        "date": "2026-05-08",
        "clock_in": "07:00",
        "clock_out": "17:30",
        "status": "present",
        "hours_worked": 10,
        "overtime_hours": 2,
        "location": "Field A",
        "photo_verified": true,
        "notes": null,
        "id": 26,
        "created_at": "2026-05-10 04:09:00"
      },
      {
        "worker_id": 3,
        "worker_name": "Peter Kamau",
        "date": "2026-05-08",
        "clock_in": "07:04",
        "clock_out": "17:30",
        "status": "present",
        "hours_worked": 10,
        "overtime_hours": 2,
        "location": "Barn A",
        "photo_verified": true,
        "notes": null,
        "id": 27,
        "created_at": "2026-05-10 04:09:00"
      },
      {
        "worker_id": 4,
        "worker_name": "Grace Wanjiku",
        "date": "2026-05-08",
        "clock_in": null,
        "clock_out": null,
        "status": "on_leave",
        "hours_worked": 0,
        "overtime_hours": 0,
        "location": null,
        "photo_verified": false,
        "notes": null,
        "id": 28,
        "created_at": "2026-05-10 04:09:00"
      },
      {
        "worker_id": 5,
        "worker_name": "David Otieno",
        "date": "2026-05-08",
        "clock_in": "07:12",
        "clock_out": "17:30",
        "status": "present",
        "hours_worked": 10,
        "overtime_hours": 2,
        "location": "Field D",
        "photo_verified": true,
        "notes": null,
        "id": 29,
        "created_at": "2026-05-10 04:09:00"
      },
      {
        "worker_id": 6,
        "worker_name": "Mary Njeri",
        "date": "2026-05-08",
        "clock_in": "07:16",
        "clock_out": "17:30",
        "status": "present",
        "hours_worked": 10,
        "overtime_hours": 2,
        "location": "Field C",
        "photo_verified": true,
        "notes": null,
        "id": 30,
        "created_at": "2026-05-10 04:09:00"
      },
      {
        "worker_id": 7,
        "worker_name": "Samuel Kibet",
        "date": "2026-05-08",
        "clock_in": "07:20",
        "clock_out": "17:30",
        "status": "present",
        "hours_worked": 10,
        "overtime_hours": 2,
        "location": "Field E",
        "photo_verified": true,
        "notes": null,
        "id": 31,
        "created_at": "2026-05-10 04:09:00"
      },
      {
        "worker_id": 8,
        "worker_name": "Aisha Hassan",
        "date": "2026-05-08",
        "clock_in": null,
        "clock_out": null,
        "status": "on_leave",
        "hours_worked": 0,
        "overtime_hours": 0,
        "location": null,
        "photo_verified": false,
        "notes": null,
        "id": 32,
        "created_at": "2026-05-10 04:09:00"
      },
      {
        "worker_id": 1,
        "worker_name": "James Mwangi",
        "date": "2026-05-09",
        "clock_in": "07:26",
        "clock_out": null,
        "status": "present",
        "hours_worked": null,
        "overtime_hours": null,
        "location": "Farm Office",
        "photo_verified": true,
        "notes": null,
        "id": 33,
        "created_at": "2026-05-10 04:09:00"
      },
      {
        "worker_id": 2,
        "worker_name": "Fatuma Ochieng",
        "date": "2026-05-09",
        "clock_in": "07:00",
        "clock_out": "17:30",
        "status": "present",
        "hours_worked": 10,
        "overtime_hours": 2,
        "location": "Field A",
        "photo_verified": true,
        "notes": null,
        "id": 34,
        "created_at": "2026-05-10 04:09:00"
      },
      {
        "worker_id": 3,
        "worker_name": "Peter Kamau",
        "date": "2026-05-09",
        "clock_in": "07:04",
        "clock_out": null,
        "status": "present",
        "hours_worked": null,
        "overtime_hours": null,
        "location": "Barn A",
        "photo_verified": true,
        "notes": null,
        "id": 35,
        "created_at": "2026-05-10 04:09:00"
      },
      {
        "worker_id": 4,
        "worker_name": "Grace Wanjiku",
        "date": "2026-05-09",
        "clock_in": null,
        "clock_out": null,
        "status": "on_leave",
        "hours_worked": 0,
        "overtime_hours": 0,
        "location": null,
        "photo_verified": false,
        "notes": null,
        "id": 36,
        "created_at": "2026-05-10 04:09:00"
      },
      {
        "worker_id": 5,
        "worker_name": "David Otieno",
        "date": "2026-05-09",
        "clock_in": "08:35",
        "clock_out": null,
        "status": "late",
        "hours_worked": null,
        "overtime_hours": null,
        "location": "Field D",
        "photo_verified": true,
        "notes": "Late arrival at 08:35",
        "id": 37,
        "created_at": "2026-05-10 04:09:00"
      },
      {
        "worker_id": 6,
        "worker_name": "Mary Njeri",
        "date": "2026-05-09",
        "clock_in": "07:16",
        "clock_out": "17:30",
        "status": "present",
        "hours_worked": 10,
        "overtime_hours": 2,
        "location": "Field C",
        "photo_verified": true,
        "notes": null,
        "id": 38,
        "created_at": "2026-05-10 04:09:00"
      },
      {
        "worker_id": 7,
        "worker_name": "Samuel Kibet",
        "date": "2026-05-09",
        "clock_in": null,
        "clock_out": null,
        "status": "absent",
        "hours_worked": 0,
        "overtime_hours": 0,
        "location": "Field E",
        "photo_verified": false,
        "notes": null,
        "id": 39,
        "created_at": "2026-05-10 04:09:00"
      },
      {
        "worker_id": 8,
        "worker_name": "Aisha Hassan",
        "date": "2026-05-09",
        "clock_in": null,
        "clock_out": null,
        "status": "on_leave",
        "hours_worked": 0,
        "overtime_hours": 0,
        "location": null,
        "photo_verified": false,
        "notes": null,
        "id": 40,
        "created_at": "2026-05-10 04:09:00"
      }
    ],
    "seq": 40
  },
  "tasks": {
    "rows": [
      {
        "worker_id": 2,
        "worker_name": "Fatuma Ochieng",
        "title": "Inspect wheat growth stages — Field A",
        "field": "Field A",
        "category": "inspection",
        "date": "2026-05-09",
        "priority": "high",
        "status": "in_progress",
        "assigned_by": "James Mwangi",
        "estimated_hours": 3,
        "actual_hours": null,
        "notes": "Check for rust disease and nutrient deficiency",
        "id": 1,
        "created_at": "2026-05-10 04:09:00"
      },
      {
        "worker_id": 5,
        "worker_name": "David Otieno",
        "title": "Apply NPK fertilizer — Field D",
        "field": "Field D",
        "category": "fertilizing",
        "date": "2026-05-09",
        "priority": "high",
        "status": "in_progress",
        "assigned_by": "James Mwangi",
        "estimated_hours": 4,
        "actual_hours": null,
        "notes": "Top dress Sunflowers with 50kg bags",
        "id": 2,
        "created_at": "2026-05-10 04:09:00"
      },
      {
        "worker_id": 3,
        "worker_name": "Peter Kamau",
        "title": "Livestock health check — Barn A",
        "field": "Barn A",
        "category": "livestock",
        "date": "2026-05-09",
        "priority": "high",
        "status": "completed",
        "assigned_by": "James Mwangi",
        "estimated_hours": 2,
        "actual_hours": 2,
        "notes": "Visual inspection + weight recording",
        "id": 3,
        "created_at": "2026-05-10 04:09:00"
      },
      {
        "worker_id": 7,
        "worker_name": "Samuel Kibet",
        "title": "Repair irrigation pipe — Section E-3",
        "field": "Field E",
        "category": "maintenance",
        "date": "2026-05-09",
        "priority": "urgent",
        "status": "pending",
        "assigned_by": "Mary Njeri",
        "estimated_hours": 3,
        "actual_hours": null,
        "notes": "Leaking joint near pump station",
        "id": 4,
        "created_at": "2026-05-10 04:09:00"
      },
      {
        "worker_id": 6,
        "worker_name": "Mary Njeri",
        "title": "Supervise tomato harvest — Greenhouse 1",
        "field": "Greenhouse 1",
        "category": "harvesting",
        "date": "2026-05-09",
        "priority": "medium",
        "status": "completed",
        "assigned_by": "James Mwangi",
        "estimated_hours": 4,
        "actual_hours": 3.5,
        "notes": "Coordinate picking team",
        "id": 5,
        "created_at": "2026-05-10 04:09:00"
      },
      {
        "worker_id": 1,
        "worker_name": "James Mwangi",
        "title": "Weekly farm management review",
        "field": "Farm Office",
        "category": "management",
        "date": "2026-05-09",
        "priority": "medium",
        "status": "pending",
        "assigned_by": "self",
        "estimated_hours": 2,
        "actual_hours": null,
        "notes": "Review all department reports",
        "id": 6,
        "created_at": "2026-05-10 04:09:00"
      },
      {
        "worker_id": 5,
        "worker_name": "David Otieno",
        "title": "Soil preparation — Field D north section",
        "field": "Field D",
        "category": "ploughing",
        "date": "2026-05-09",
        "priority": "medium",
        "status": "pending",
        "assigned_by": "Mary Njeri",
        "estimated_hours": 5,
        "actual_hours": null,
        "notes": "Sub-soiling before rains",
        "id": 7,
        "created_at": "2026-05-10 04:09:00"
      },
      {
        "worker_id": 5,
        "worker_name": "David Otieno",
        "title": "Plough Field D for sunflower planting",
        "field": "Field D",
        "category": "ploughing",
        "date": "2026-05-08",
        "priority": "high",
        "status": "completed",
        "assigned_by": "James Mwangi",
        "estimated_hours": 8,
        "actual_hours": 9,
        "notes": "Deep plough 12 ha",
        "id": 8,
        "created_at": "2026-05-10 04:09:00"
      },
      {
        "worker_id": 3,
        "worker_name": "Peter Kamau",
        "title": "Vaccinate sheep flock — Pasture 2",
        "field": "Pasture 2",
        "category": "livestock",
        "date": "2026-05-08",
        "priority": "urgent",
        "status": "completed",
        "assigned_by": "James Mwangi",
        "estimated_hours": 3,
        "actual_hours": 2.5,
        "notes": "FMD vaccination 50 sheep",
        "id": 9,
        "created_at": "2026-05-10 04:09:00"
      },
      {
        "worker_id": 6,
        "worker_name": "Mary Njeri",
        "title": "Apply herbicide — Field C post-emergence",
        "field": "Field C",
        "category": "spraying",
        "date": "2026-05-08",
        "priority": "high",
        "status": "completed",
        "assigned_by": "Fatuma",
        "estimated_hours": 4,
        "actual_hours": 4,
        "notes": "Post-emergence soybean herbicide",
        "id": 10,
        "created_at": "2026-05-10 04:09:00"
      },
      {
        "worker_id": 7,
        "worker_name": "Samuel Kibet",
        "title": "Install drip irrigation — Greenhouse 1",
        "field": "Greenhouse 1",
        "category": "irrigation",
        "date": "2026-05-07",
        "priority": "high",
        "status": "completed",
        "assigned_by": "Mary Njeri",
        "estimated_hours": 6,
        "actual_hours": 7,
        "notes": "New drip lines for tomatoes",
        "id": 11,
        "created_at": "2026-05-10 04:09:00"
      },
      {
        "worker_id": 2,
        "worker_name": "Fatuma Ochieng",
        "title": "Soil sampling — all fields",
        "field": "All Fields",
        "category": "inspection",
        "date": "2026-05-07",
        "priority": "medium",
        "status": "completed",
        "assigned_by": "James Mwangi",
        "estimated_hours": 5,
        "actual_hours": 5.5,
        "notes": "Collect for lab analysis",
        "id": 12,
        "created_at": "2026-05-10 04:09:00"
      },
      {
        "worker_id": 2,
        "worker_name": "Fatuma Ochieng",
        "title": "Weekly disease surveillance — Field A",
        "field": "Field A",
        "category": "inspection",
        "date": "2026-05-10",
        "priority": "medium",
        "status": "pending",
        "assigned_by": "James Mwangi",
        "estimated_hours": 2,
        "actual_hours": null,
        "notes": "Monitor rust and aphid populations",
        "id": 13,
        "created_at": "2026-05-10 04:09:00"
      },
      {
        "worker_id": 5,
        "worker_name": "David Otieno",
        "title": "Combine harvester pre-season service",
        "field": "Equipment Yard",
        "category": "maintenance",
        "date": "2026-05-11",
        "priority": "high",
        "status": "pending",
        "assigned_by": "James Mwangi",
        "estimated_hours": 6,
        "actual_hours": null,
        "notes": "Full service before wheat harvest",
        "id": 14,
        "created_at": "2026-05-10 04:09:00"
      },
      {
        "worker_id": 3,
        "worker_name": "Peter Kamau",
        "title": "Deworming — all cattle",
        "field": "Barn A",
        "category": "livestock",
        "date": "2026-05-12",
        "priority": "high",
        "status": "pending",
        "assigned_by": "James Mwangi",
        "estimated_hours": 3,
        "actual_hours": null,
        "notes": "Cattle in Barn A and Pasture 1",
        "id": 15,
        "created_at": "2026-05-10 04:09:00"
      },
      {
        "worker_id": 7,
        "worker_name": "Samuel Kibet",
        "title": "Irrigation system winter check — Field E",
        "field": "Field E",
        "category": "irrigation",
        "date": "2026-05-13",
        "priority": "medium",
        "status": "pending",
        "assigned_by": "Mary Njeri",
        "estimated_hours": 4,
        "actual_hours": null,
        "notes": "Full system pressure test",
        "id": 16,
        "created_at": "2026-05-10 04:09:00"
      }
    ],
    "seq": 16
  },
  "users": {
    "rows": [
      {
        "name": "Admin User",
        "email": "admin@agrifarm.com",
        "phone": "0700-000-001",
        "role": "super_admin",
        "status": "active",
        "farm_ids": [
          1,
          2
        ],
        "avatar_color": "bg-red-500",
        "last_login": "2026-05-10 22:11:43",
        "password_hash": "hashed_admin123",
        "id": 1,
        "created_at": "2026-05-10 04:22:01"
      },
      {
        "name": "James Mwangi",
        "email": "james@farm.com",
        "phone": "0712-345-678",
        "role": "farm_manager",
        "status": "active",
        "farm_ids": [
          1
        ],
        "avatar_color": "bg-blue-600",
        "last_login": "2026-05-10 07:45:00",
        "password_hash": "hashed_james123",
        "id": 2,
        "created_at": "2026-05-10 04:22:01"
      },
      {
        "name": "Fatuma Ochieng",
        "email": "fatuma@farm.com",
        "phone": "0723-456-789",
        "role": "agronomist",
        "status": "active",
        "farm_ids": [
          1
        ],
        "avatar_color": "bg-green-600",
        "last_login": "2026-05-09 08:10:00",
        "password_hash": "hashed_fatuma123",
        "id": 3,
        "created_at": "2026-05-10 04:22:01"
      },
      {
        "name": "Peter Kamau",
        "email": "peter@farm.com",
        "phone": "0734-567-890",
        "role": "worker",
        "status": "active",
        "farm_ids": [
          1
        ],
        "avatar_color": "bg-purple-500",
        "last_login": "2026-05-10 07:52:00",
        "password_hash": "hashed_peter123",
        "id": 4,
        "created_at": "2026-05-10 04:22:01"
      },
      {
        "name": "Grace Wanjiku",
        "email": "grace@farm.com",
        "phone": "0745-678-901",
        "role": "accountant",
        "status": "active",
        "farm_ids": [
          1,
          2
        ],
        "avatar_color": "bg-yellow-600",
        "last_login": "2026-05-09 09:00:00",
        "password_hash": "hashed_grace123",
        "id": 5,
        "created_at": "2026-05-10 04:22:01"
      },
      {
        "name": "David Otieno",
        "email": "david@farm.com",
        "phone": "0756-789-012",
        "role": "worker",
        "status": "active",
        "farm_ids": [
          1
        ],
        "avatar_color": "bg-orange-500",
        "last_login": "2026-05-10 07:30:00",
        "password_hash": "hashed_david123",
        "id": 6,
        "created_at": "2026-05-10 04:22:01"
      },
      {
        "name": "Mary Njeri",
        "email": "mary@farm.com",
        "phone": "0767-890-123",
        "role": "farm_manager",
        "status": "active",
        "farm_ids": [
          2
        ],
        "avatar_color": "bg-teal-500",
        "last_login": "2026-05-08 08:00:00",
        "password_hash": "hashed_mary123",
        "id": 7,
        "created_at": "2026-05-10 04:22:01"
      },
      {
        "name": "Samuel Kibet",
        "email": "samuel@farm.com",
        "phone": "0778-901-234",
        "role": "worker",
        "status": "inactive",
        "farm_ids": [
          1
        ],
        "avatar_color": "bg-cyan-500",
        "last_login": "2026-05-07 07:30:00",
        "password_hash": "hashed_samuel123",
        "id": 8,
        "created_at": "2026-05-10 04:22:01"
      },
      {
        "name": "Aisha Hassan",
        "email": "aisha@farm.com",
        "phone": "0789-012-345",
        "role": "accountant",
        "status": "suspended",
        "farm_ids": [
          1
        ],
        "avatar_color": "bg-pink-500",
        "last_login": "2026-04-30 09:15:00",
        "password_hash": "hashed_aisha123",
        "id": 9,
        "created_at": "2026-05-10 04:22:01"
      },
      {
        "name": "Demo Viewer",
        "email": "demo@agrifarm.com",
        "phone": "0700-000-010",
        "role": "worker",
        "status": "active",
        "farm_ids": [
          1,
          2
        ],
        "avatar_color": "bg-gray-500",
        "last_login": "2026-05-10 06:00:00",
        "password_hash": "hashed_demo123",
        "id": 10,
        "created_at": "2026-05-10 04:22:01"
      },
      {
        "name": "Merhawi gulwet",
        "email": "merhawigu@gmail.com",
        "phone": null,
        "role": "farm_manager",
        "status": "active",
        "farm_ids": [],
        "avatar_color": "bg-orange-500",
        "password_hash": "$2b$10$6N.Ql6aEq34o1OqNahe1duqRZrP9DcWA/XlI5AImBxZqRHBKdeE3u",
        "last_login": "2026-05-10 21:33:30",
        "id": 11,
        "created_at": "2026-05-10 20:18:07"
      },
      {
        "name": "Merhawi gulwet",
        "email": "meradeki@gmail.com",
        "phone": null,
        "role": "agronomist",
        "status": "active",
        "farm_ids": [],
        "avatar_color": "bg-orange-500",
        "password_hash": "$2b$10$j.tYCInWIb8VeHMTRW8Ne.zyENUyXdO.4MVfmQQOhIBpQ/2X.n9uy",
        "last_login": "2026-05-10 20:33:15",
        "id": 12,
        "created_at": "2026-05-10 20:33:15"
      },
      {
        "name": "mera",
        "email": "samera3031@gmail.com",
        "phone": null,
        "role": "worker",
        "status": "active",
        "farm_ids": [
          3
        ],
        "avatar_color": "bg-green-600",
        "password_hash": "$2b$10$sAuIpd65fboVca68TRAC6ueYS/rMkbm/Ze6Y3hIJdrdABsuYQdl3S",
        "last_login": "2026-05-10 21:43:01",
        "id": 13,
        "created_at": "2026-05-10 21:43:01"
      },
      {
        "name": "fani",
        "email": "test@gmail.com",
        "phone": null,
        "role": "accountant",
        "status": "active",
        "farm_ids": [
          4
        ],
        "avatar_color": "bg-blue-600",
        "password_hash": "$2b$10$SCwEdysByH2VmlloaS3nT.WkYvIoIHCuyrniFGn9/UtudYE4gJeCK",
        "last_login": "2026-05-10 22:01:22",
        "id": 14,
        "created_at": "2026-05-10 22:01:22"
      }
    ],
    "seq": 14
  },
  "farms": {
    "rows": [
      {
        "name": "Mwangi Family Farm",
        "owner": "James Mwangi",
        "location": "Nakuru County, Kenya",
        "total_area_ha": 108,
        "farm_type": "Mixed",
        "status": "active",
        "established": "2010-03-01",
        "phone": "0712-345-678",
        "email": "james@farm.com",
        "description": "Large mixed farm with crops, livestock and horticulture",
        "gps_lat": -0.3031,
        "gps_lng": 36.08,
        "boundary": "[{\"lat\":-0.299,\"lng\":36.075},{\"lat\":-0.299,\"lng\":36.087},{\"lat\":-0.3075,\"lng\":36.087},{\"lat\":-0.3075,\"lng\":36.075}]",
        "soil": "{\"type\":\"Clay Loam\",\"ph\":6.2,\"organic_matter\":3.8,\"nitrogen\":\"medium\",\"phosphorus\":\"high\",\"potassium\":\"medium\",\"last_tested\":\"2026-03-15\",\"lab\":\"Kenya Soil Health Labs\"}",
        "fields": "[{\"name\":\"Field A\",\"area_ha\":25.5,\"crop\":\"Wheat\",\"soil_type\":\"Clay Loam\",\"irrigation\":\"center pivot\"},{\"name\":\"Field B\",\"area_ha\":18,\"crop\":\"Corn\",\"soil_type\":\"Sandy Loam\",\"irrigation\":\"drip\"},{\"name\":\"Field C\",\"area_ha\":30,\"crop\":\"Soybeans\",\"soil_type\":\"Clay Loam\",\"irrigation\":\"furrow\"},{\"name\":\"Field D\",\"area_ha\":12,\"crop\":\"Sunflowers\",\"soil_type\":\"Loam\",\"irrigation\":\"none\"},{\"name\":\"Field E\",\"area_ha\":20,\"crop\":\"Rice\",\"soil_type\":\"Clay\",\"irrigation\":\"flood\"},{\"name\":\"Greenhouse 1\",\"area_ha\":2.5,\"crop\":\"Tomatoes\",\"soil_type\":\"Potting mix\",\"irrigation\":\"drip\"}]",
        "id": 1,
        "created_at": "2026-05-10 04:22:01"
      },
      {
        "name": "Green Valley Horticultural Farm",
        "owner": "Mary Njeri",
        "location": "Kiambu County, Kenya",
        "total_area_ha": 45,
        "farm_type": "Horticulture",
        "status": "active",
        "established": "2018-06-01",
        "phone": "0767-890-123",
        "email": "mary@greenvalley.com",
        "description": "Specialised horticultural farm for export vegetables",
        "gps_lat": -1.032,
        "gps_lng": 37.07,
        "boundary": "[{\"lat\":-1.03,\"lng\":37.067},{\"lat\":-1.03,\"lng\":37.073},{\"lat\":-1.034,\"lng\":37.073},{\"lat\":-1.034,\"lng\":37.067}]",
        "soil": "{\"type\":\"Sandy Loam\",\"ph\":6.8,\"organic_matter\":5.2,\"nitrogen\":\"high\",\"phosphorus\":\"medium\",\"potassium\":\"high\",\"last_tested\":\"2026-02-20\",\"lab\":\"AgroTest Kenya\"}",
        "fields": "[{\"name\":\"Block 1\",\"area_ha\":15,\"crop\":\"French Beans\",\"soil_type\":\"Sandy Loam\",\"irrigation\":\"drip\"},{\"name\":\"Block 2\",\"area_ha\":12,\"crop\":\"Snow Peas\",\"soil_type\":\"Sandy Loam\",\"irrigation\":\"drip\"},{\"name\":\"Block 3\",\"area_ha\":10,\"crop\":\"Capsicum\",\"soil_type\":\"Loam\",\"irrigation\":\"drip\"},{\"name\":\"Greenhouse A\",\"area_ha\":4,\"crop\":\"Roses\",\"soil_type\":\"Potting mix\",\"irrigation\":\"drip\"},{\"name\":\"Greenhouse B\",\"area_ha\":4,\"crop\":\"Herbs\",\"soil_type\":\"Potting mix\",\"irrigation\":\"drip\"}]",
        "id": 2,
        "created_at": "2026-05-10 04:22:01"
      },
      {
        "name": "test",
        "owner": "mera",
        "location": "Kenya",
        "total_area_ha": 0,
        "farm_type": "Mixed",
        "status": "active",
        "established": "2026-05-10",
        "phone": null,
        "email": "samera3031@gmail.com",
        "gps_lat": null,
        "gps_lng": null,
        "soil": null,
        "fields": "[]",
        "boundary": "[]",
        "id": 3,
        "created_at": "2026-05-10 21:43:01"
      },
      {
        "name": "asmera",
        "owner": "fani",
        "location": "Kenya",
        "total_area_ha": 0,
        "farm_type": "Mixed",
        "status": "active",
        "established": "2026-05-10",
        "phone": null,
        "email": "test@gmail.com",
        "gps_lat": null,
        "gps_lng": null,
        "soil": null,
        "fields": "[]",
        "boundary": "[]",
        "id": 4,
        "created_at": "2026-05-10 22:01:22"
      }
    ],
    "seq": 4
  },
  "payroll": {
    "rows": [
      {
        "worker_id": 1,
        "worker_name": "James Mwangi",
        "role": "Farm Manager",
        "department": "Management",
        "month": "2026-05",
        "base_salary": 85000,
        "working_days": 21,
        "days_worked": 5,
        "days_absent": 0,
        "leave_days": 0,
        "overtime_hours": 8,
        "overtime_pay": 6071,
        "gross_pay": 26310,
        "nhif": 1200,
        "nssf": 2160,
        "paye": 231,
        "total_deductions": 3591,
        "net_pay": 22719,
        "status": "pending",
        "id": 1,
        "created_at": "2026-05-10 04:33:11"
      },
      {
        "worker_id": 2,
        "worker_name": "Fatuma Ochieng",
        "role": "Agronomist",
        "department": "Agronomy",
        "month": "2026-05",
        "base_salary": 65000,
        "working_days": 21,
        "days_worked": 5,
        "days_absent": 0,
        "leave_days": 0,
        "overtime_hours": 8.7,
        "overtime_pay": 5049,
        "gross_pay": 20525,
        "nhif": 1200,
        "nssf": 2160,
        "paye": 0,
        "total_deductions": 3360,
        "net_pay": 17165,
        "status": "pending",
        "id": 2,
        "created_at": "2026-05-10 04:33:11"
      },
      {
        "worker_id": 3,
        "worker_name": "Peter Kamau",
        "role": "Livestock Supervisor",
        "department": "Livestock",
        "month": "2026-05",
        "base_salary": 55000,
        "working_days": 21,
        "days_worked": 5,
        "days_absent": 0,
        "leave_days": 0,
        "overtime_hours": 8,
        "overtime_pay": 3929,
        "gross_pay": 17024,
        "nhif": 1200,
        "nssf": 2160,
        "paye": 0,
        "total_deductions": 3360,
        "net_pay": 13664,
        "status": "pending",
        "id": 3,
        "created_at": "2026-05-10 04:33:11"
      },
      {
        "worker_id": 4,
        "worker_name": "Grace Wanjiku",
        "role": "Finance Officer",
        "department": "Finance",
        "month": "2026-05",
        "base_salary": 60000,
        "working_days": 21,
        "days_worked": 21,
        "days_absent": 0,
        "leave_days": 5,
        "overtime_hours": 0,
        "overtime_pay": 0,
        "gross_pay": 60000,
        "nhif": 1200,
        "nssf": 2160,
        "paye": 3600,
        "total_deductions": 6960,
        "net_pay": 53040,
        "status": "pending",
        "id": 4,
        "created_at": "2026-05-10 04:33:11"
      },
      {
        "worker_id": 5,
        "worker_name": "David Otieno",
        "role": "Equipment Operator",
        "department": "Operations",
        "month": "2026-05",
        "base_salary": 42000,
        "working_days": 21,
        "days_worked": 5,
        "days_absent": 0,
        "leave_days": 0,
        "overtime_hours": 6.7,
        "overtime_pay": 2513,
        "gross_pay": 12513,
        "nhif": 600,
        "nssf": 2160,
        "paye": 0,
        "total_deductions": 2760,
        "net_pay": 9753,
        "status": "pending",
        "id": 5,
        "created_at": "2026-05-10 04:33:11"
      },
      {
        "worker_id": 6,
        "worker_name": "Mary Njeri",
        "role": "Field Supervisor",
        "department": "Operations",
        "month": "2026-05",
        "base_salary": 48000,
        "working_days": 21,
        "days_worked": 5,
        "days_absent": 0,
        "leave_days": 0,
        "overtime_hours": 10,
        "overtime_pay": 4286,
        "gross_pay": 15714,
        "nhif": 600,
        "nssf": 2160,
        "paye": 0,
        "total_deductions": 2760,
        "net_pay": 12954,
        "status": "pending",
        "id": 6,
        "created_at": "2026-05-10 04:33:11"
      },
      {
        "worker_id": 7,
        "worker_name": "Samuel Kibet",
        "role": "Irrigation Technician",
        "department": "Operations",
        "month": "2026-05",
        "base_salary": 40000,
        "working_days": 21,
        "days_worked": 3,
        "days_absent": 2,
        "leave_days": 0,
        "overtime_hours": 6,
        "overtime_pay": 2143,
        "gross_pay": 7857,
        "nhif": 600,
        "nssf": 2160,
        "paye": 0,
        "total_deductions": 2760,
        "net_pay": 5097,
        "status": "pending",
        "id": 7,
        "created_at": "2026-05-10 04:33:11"
      },
      {
        "worker_id": 8,
        "worker_name": "Aisha Hassan",
        "role": "Accountant",
        "department": "Finance",
        "month": "2026-05",
        "base_salary": 55000,
        "working_days": 21,
        "days_worked": 0,
        "days_absent": 0,
        "leave_days": 5,
        "overtime_hours": 0,
        "overtime_pay": 0,
        "gross_pay": 55000,
        "nhif": 1200,
        "nssf": 2160,
        "paye": 0,
        "total_deductions": 3360,
        "net_pay": 51640,
        "status": "pending",
        "id": 8,
        "created_at": "2026-05-10 04:33:11"
      }
    ],
    "seq": 8
  },
  "marketplace_products": {
    "rows": [
      {
        "seller_id": 1,
        "seller_name": "James Mwangi",
        "title": "Fresh Wheat Grain",
        "category": "Grains",
        "quantity": 5000,
        "unit": "kg",
        "price_kes": 22,
        "location": "Nakuru, Kenya",
        "description": "Grade A winter wheat, clean and dry. Ready for milling.",
        "status": "active",
        "views": 42,
        "id": 1,
        "created_at": "2026-05-10 20:05:17"
      },
      {
        "seller_id": 1,
        "seller_name": "James Mwangi",
        "title": "Dried Soybeans",
        "category": "Grains",
        "quantity": 3000,
        "unit": "kg",
        "price_kes": 45,
        "location": "Nakuru, Kenya",
        "description": "Non-GMO soybeans, 13% moisture. Ideal for animal feed.",
        "status": "active",
        "views": 28,
        "id": 2,
        "created_at": "2026-05-10 20:05:17"
      },
      {
        "seller_id": 2,
        "seller_name": "Fatuma Ochieng",
        "title": "Fresh Tomatoes — Roma",
        "category": "Vegetables",
        "quantity": 800,
        "unit": "kg",
        "price_kes": 80,
        "location": "Nakuru, Kenya",
        "description": "Firm Roma tomatoes, harvested today. Excellent for sauces.",
        "status": "active",
        "views": 67,
        "id": 3,
        "created_at": "2026-05-10 20:05:17"
      },
      {
        "seller_id": 3,
        "seller_name": "Peter Kamau",
        "title": "Holstein Dairy Cows",
        "category": "Livestock",
        "quantity": 3,
        "unit": "head",
        "price_kes": 95000,
        "location": "Nakuru, Kenya",
        "description": "High-yielding Holstein cows, 15-20L milk/day. Vaccinated.",
        "status": "active",
        "views": 15,
        "id": 4,
        "created_at": "2026-05-10 20:05:17"
      },
      {
        "seller_id": 3,
        "seller_name": "Peter Kamau",
        "title": "Fresh Whole Milk",
        "category": "Dairy",
        "quantity": 500,
        "unit": "L",
        "price_kes": 60,
        "location": "Nakuru, Kenya",
        "description": "Farm-fresh whole milk, tested and certified. Daily supply.",
        "status": "active",
        "views": 89,
        "id": 5,
        "created_at": "2026-05-10 20:05:17"
      },
      {
        "seller_id": 7,
        "seller_name": "Mary Njeri",
        "title": "French Beans — Export",
        "category": "Vegetables",
        "quantity": 600,
        "unit": "kg",
        "price_kes": 120,
        "location": "Kiambu, Kenya",
        "description": "Air-freight grade French beans, fine quality for export.",
        "status": "active",
        "views": 54,
        "id": 6,
        "created_at": "2026-05-10 20:05:17"
      },
      {
        "seller_id": 7,
        "seller_name": "Mary Njeri",
        "title": "Snow Peas",
        "category": "Vegetables",
        "quantity": 400,
        "unit": "kg",
        "price_kes": 150,
        "location": "Kiambu, Kenya",
        "description": "Export-grade snow peas, pre-cooled and sorted.",
        "status": "active",
        "views": 31,
        "id": 7,
        "created_at": "2026-05-10 20:05:17"
      },
      {
        "seller_id": 1,
        "seller_name": "James Mwangi",
        "title": "Corn (Yellow Maize)",
        "category": "Grains",
        "quantity": 8000,
        "unit": "kg",
        "price_kes": 20,
        "location": "Nakuru, Kenya",
        "description": "Dry yellow maize, aflatoxin tested. Ideal for milling.",
        "status": "active",
        "views": 76,
        "id": 8,
        "created_at": "2026-05-10 20:05:17"
      },
      {
        "seller_id": 3,
        "seller_name": "Peter Kamau",
        "title": "Boer Goat (Live)",
        "category": "Livestock",
        "quantity": 8,
        "unit": "head",
        "price_kes": 18000,
        "location": "Nakuru, Kenya",
        "description": "Healthy Boer goats 25-30kg. All vaccinated and dewormed.",
        "status": "active",
        "views": 22,
        "id": 9,
        "created_at": "2026-05-10 20:05:17"
      },
      {
        "seller_id": 6,
        "seller_name": "Samuel Kibet",
        "title": "Sunflower Seeds",
        "category": "Oilseeds",
        "quantity": 2000,
        "unit": "kg",
        "price_kes": 35,
        "location": "Nakuru, Kenya",
        "description": "Hybrid sunflower seeds, high oil content, clean grade.",
        "status": "sold_out",
        "views": 19,
        "id": 10,
        "created_at": "2026-05-10 20:05:17"
      }
    ],
    "seq": 10
  },
  "marketplace_buyers": {
    "rows": [
      {
        "name": "Nairobi Millers Ltd",
        "phone": "+254-20-123-4567",
        "email": "procurement@nairobimill.co.ke",
        "location": "Nairobi",
        "type": "Processor",
        "total_orders": 4,
        "id": 1,
        "created_at": "2026-05-10 20:05:17"
      },
      {
        "name": "City Fresh Market",
        "phone": "+254-722-234-567",
        "email": "buying@cityfresh.co.ke",
        "location": "Nairobi",
        "type": "Retailer",
        "total_orders": 6,
        "id": 2,
        "created_at": "2026-05-10 20:05:17"
      },
      {
        "name": "Dairy Cooperative KE",
        "phone": "+254-733-345-678",
        "email": "supply@dairykoop.co.ke",
        "location": "Nakuru",
        "type": "Cooperative",
        "total_orders": 3,
        "id": 3,
        "created_at": "2026-05-10 20:05:17"
      },
      {
        "name": "Meat Master Ltd",
        "phone": "+254-744-456-789",
        "email": "orders@meatmaster.co.ke",
        "location": "Nairobi",
        "type": "Processor",
        "total_orders": 2,
        "id": 4,
        "created_at": "2026-05-10 20:05:17"
      },
      {
        "name": "Organic Africa Exports",
        "phone": "+254-755-567-890",
        "email": "import@organicafrica.com",
        "location": "Mombasa",
        "type": "Exporter",
        "total_orders": 5,
        "id": 5,
        "created_at": "2026-05-10 20:05:17"
      },
      {
        "name": "James Otieno (Individual)",
        "phone": "+254-700-111-222",
        "email": "jotieno@gmail.com",
        "location": "Kisumu",
        "type": "Individual",
        "total_orders": 1,
        "id": 6,
        "created_at": "2026-05-10 20:05:17"
      }
    ],
    "seq": 6
  },
  "marketplace_orders": {
    "rows": [
      {
        "product_id": 1,
        "product_title": "Fresh Wheat Grain",
        "product_category": "Grains",
        "seller_id": 1,
        "seller_name": "James Mwangi",
        "buyer_id": 1,
        "buyer_name": "Nairobi Millers Ltd",
        "buyer_phone": "+254-20-123-4567",
        "quantity": 2000,
        "unit": "kg",
        "unit_price": 22,
        "total_amount": 44000,
        "status": "delivered",
        "payment_method": "bank_transfer",
        "delivery_address": "Industrial Area, Nairobi",
        "id": 1,
        "created_at": "2026-05-10 20:05:17"
      },
      {
        "product_id": 3,
        "product_title": "Fresh Tomatoes — Roma",
        "product_category": "Vegetables",
        "seller_id": 2,
        "seller_name": "Fatuma Ochieng",
        "buyer_id": 2,
        "buyer_name": "City Fresh Market",
        "buyer_phone": "+254-722-234-567",
        "quantity": 300,
        "unit": "kg",
        "unit_price": 80,
        "total_amount": 24000,
        "status": "shipped",
        "payment_method": "mpesa",
        "delivery_address": "Westlands, Nairobi",
        "id": 2,
        "created_at": "2026-05-10 20:05:17"
      },
      {
        "product_id": 5,
        "product_title": "Fresh Whole Milk",
        "product_category": "Dairy",
        "seller_id": 3,
        "seller_name": "Peter Kamau",
        "buyer_id": 3,
        "buyer_name": "Dairy Cooperative KE",
        "buyer_phone": "+254-733-345-678",
        "quantity": 200,
        "unit": "L",
        "unit_price": 60,
        "total_amount": 12000,
        "status": "confirmed",
        "payment_method": "bank_transfer",
        "delivery_address": "Cooperative HQ, Nakuru",
        "id": 3,
        "created_at": "2026-05-10 20:05:17"
      },
      {
        "product_id": 8,
        "product_title": "Corn (Yellow Maize)",
        "product_category": "Grains",
        "seller_id": 1,
        "seller_name": "James Mwangi",
        "buyer_id": 1,
        "buyer_name": "Nairobi Millers Ltd",
        "buyer_phone": "+254-20-123-4567",
        "quantity": 3000,
        "unit": "kg",
        "unit_price": 20,
        "total_amount": 60000,
        "status": "pending",
        "payment_method": "bank_transfer",
        "delivery_address": "Industrial Area, Nairobi",
        "id": 4,
        "created_at": "2026-05-10 20:05:17"
      },
      {
        "product_id": 6,
        "product_title": "French Beans — Export",
        "product_category": "Vegetables",
        "seller_id": 7,
        "seller_name": "Mary Njeri",
        "buyer_id": 5,
        "buyer_name": "Organic Africa Exports",
        "buyer_phone": "+254-755-567-890",
        "quantity": 400,
        "unit": "kg",
        "unit_price": 120,
        "total_amount": 48000,
        "status": "delivered",
        "payment_method": "bank_transfer",
        "delivery_address": "Mombasa Port",
        "id": 5,
        "created_at": "2026-05-10 20:05:17"
      },
      {
        "product_id": 9,
        "product_title": "Boer Goat (Live)",
        "product_category": "Livestock",
        "seller_id": 3,
        "seller_name": "Peter Kamau",
        "buyer_id": 4,
        "buyer_name": "Meat Master Ltd",
        "buyer_phone": "+254-744-456-789",
        "quantity": 5,
        "unit": "head",
        "unit_price": 18000,
        "total_amount": 90000,
        "status": "confirmed",
        "payment_method": "bank_transfer",
        "delivery_address": "Industrial Area, Nairobi",
        "id": 6,
        "created_at": "2026-05-10 20:05:17"
      },
      {
        "product_id": 2,
        "product_title": "Dried Soybeans",
        "product_category": "Grains",
        "seller_id": 1,
        "seller_name": "James Mwangi",
        "buyer_id": 6,
        "buyer_name": "James Otieno (Individual)",
        "buyer_phone": "+254-700-111-222",
        "quantity": 50,
        "unit": "kg",
        "unit_price": 45,
        "total_amount": 2250,
        "status": "pending",
        "payment_method": "mpesa",
        "delivery_address": "Kisumu Town",
        "id": 7,
        "created_at": "2026-05-10 20:05:17"
      }
    ],
    "seq": 7
  },
  "marketplace_deliveries": {
    "rows": [
      {
        "order_id": 1,
        "order_ref": "ORD-0001",
        "buyer_name": "Nairobi Millers Ltd",
        "buyer_phone": "+254-20-123-4567",
        "product_title": "Fresh Wheat Grain",
        "quantity": 2000,
        "unit": "kg",
        "delivery_address": "Industrial Area, Nairobi",
        "status": "delivered",
        "driver_name": "John Kamau",
        "vehicle": "KBZ 123A — 5T Lorry",
        "pickup_time": "2026-05-05 07:00",
        "delivery_time": "2026-05-05 14:30",
        "tracking_notes": "Delivered and signed for.",
        "id": 1,
        "created_at": "2026-05-10 20:05:17"
      },
      {
        "order_id": 2,
        "order_ref": "ORD-0002",
        "buyer_name": "City Fresh Market",
        "buyer_phone": "+254-722-234-567",
        "product_title": "Fresh Tomatoes — Roma",
        "quantity": 300,
        "unit": "kg",
        "delivery_address": "Westlands, Nairobi",
        "status": "in_transit",
        "driver_name": "Mary Wanjiru",
        "vehicle": "KCB 456B — Pickup",
        "pickup_time": "2026-05-09 06:00",
        "delivery_time": null,
        "tracking_notes": "Departed Nakuru 06:00. ETA Nairobi 10:00.",
        "id": 2,
        "created_at": "2026-05-10 20:05:17"
      },
      {
        "order_id": 3,
        "order_ref": "ORD-0003",
        "buyer_name": "Dairy Cooperative KE",
        "buyer_phone": "+254-733-345-678",
        "product_title": "Fresh Whole Milk",
        "quantity": 200,
        "unit": "L",
        "delivery_address": "Cooperative HQ, Nakuru",
        "status": "scheduled",
        "driver_name": "Samuel Oloo",
        "vehicle": "KDA 789C — Milk Van",
        "pickup_time": "2026-05-10 05:30",
        "delivery_time": null,
        "tracking_notes": "Scheduled for tomorrow morning pickup.",
        "id": 3,
        "created_at": "2026-05-10 20:05:17"
      },
      {
        "order_id": 5,
        "order_ref": "ORD-0005",
        "buyer_name": "Organic Africa Exports",
        "buyer_phone": "+254-755-567-890",
        "product_title": "French Beans — Export",
        "quantity": 400,
        "unit": "kg",
        "delivery_address": "Mombasa Port",
        "status": "delivered",
        "driver_name": "Hassan Ali",
        "vehicle": "KDB 321F — Reefer",
        "pickup_time": "2026-05-07 04:00",
        "delivery_time": "2026-05-07 16:00",
        "tracking_notes": "Cold-chain maintained. Delivered to port.",
        "id": 4,
        "created_at": "2026-05-10 20:05:17"
      },
      {
        "order_id": 6,
        "order_ref": "ORD-0006",
        "buyer_name": "Meat Master Ltd",
        "buyer_phone": "+254-744-456-789",
        "product_title": "Boer Goat (Live)",
        "quantity": 5,
        "unit": "head",
        "delivery_address": "Industrial Area, Nairobi",
        "status": "scheduled",
        "driver_name": null,
        "vehicle": null,
        "pickup_time": null,
        "delivery_time": null,
        "tracking_notes": "Awaiting driver assignment.",
        "id": 5,
        "created_at": "2026-05-10 20:05:17"
      }
    ],
    "seq": 5
  },
  "notifications": {
    "rows": [
      {
        "type": "weather",
        "title": "Heavy Rain Warning",
        "message": "Heavy rainfall (45mm) expected in Nakuru from 14:00 today. Delay spraying operations and secure farm equipment.",
        "channels": [
          "in_app",
          "sms"
        ],
        "recipient_role": "all",
        "read": false,
        "created_at": "2026-05-10 20:05:17",
        "id": 1
      },
      {
        "type": "irrigation",
        "title": "Irrigation Alert — Field A",
        "message": "Soil moisture in Field A has dropped below 35% threshold. Wheat crop requires immediate irrigation.",
        "channels": [
          "in_app",
          "sms"
        ],
        "recipient_role": "farm_manager",
        "read": false,
        "created_at": "2026-05-10 20:05:17",
        "id": 2
      },
      {
        "type": "disease",
        "title": "Early Blight Detected — Greenhouse 1",
        "message": "Suspected early blight (Alternaria solani) detected on tomato plants. Isolate affected plants and apply copper fungicide.",
        "channels": [
          "in_app",
          "sms",
          "email"
        ],
        "recipient_role": "agronomist",
        "read": false,
        "created_at": "2026-05-10 20:05:17",
        "id": 3
      },
      {
        "type": "market",
        "title": "Wheat Price Alert +15%",
        "message": "Nairobi grain market: Wheat prices have risen 15% to KES 25.30/kg. Consider selling current stock.",
        "channels": [
          "in_app"
        ],
        "recipient_role": "farm_manager",
        "read": true,
        "created_at": "2026-05-10 20:05:17",
        "id": 4
      },
      {
        "type": "system",
        "title": "May 2026 Payroll Generated",
        "message": "Payroll for 8 workers has been computed for May 2026. Total payout: KES 448,000. Pending approval.",
        "channels": [
          "in_app",
          "email"
        ],
        "recipient_role": "accountant",
        "read": true,
        "created_at": "2026-05-10 20:05:17",
        "id": 5
      },
      {
        "type": "weather",
        "title": "UV Index Advisory",
        "message": "UV Index forecast at 9 (Very High) between 11:00–15:00. Ensure livestock have shade. Limit outdoor worker exposure.",
        "channels": [
          "in_app"
        ],
        "recipient_role": "all",
        "read": true,
        "created_at": "2026-05-10 20:05:17",
        "id": 6
      },
      {
        "type": "irrigation",
        "title": "Irrigation Complete — Field C",
        "message": "Scheduled irrigation for Field C (soybeans) completed successfully. 3,500L water applied. Next scheduled: 48 hours.",
        "channels": [
          "in_app"
        ],
        "recipient_role": "farm_manager",
        "read": true,
        "created_at": "2026-05-10 20:05:17",
        "id": 7
      },
      {
        "type": "disease",
        "title": "FMD Vaccination Reminder",
        "message": "Foot-and-Mouth Disease vaccination due for cattle in Barn A within 7 days. Contact vet to schedule visit.",
        "channels": [
          "in_app",
          "sms"
        ],
        "recipient_role": "farm_manager",
        "read": false,
        "created_at": "2026-05-10 20:05:17",
        "id": 8
      },
      {
        "type": "market",
        "title": "New Buyer Inquiry — Tomatoes",
        "message": "Organic Africa Exports has requested 500kg tomatoes at KES 85/kg. Check Marketplace for order details.",
        "channels": [
          "in_app"
        ],
        "recipient_role": "farm_manager",
        "read": false,
        "created_at": "2026-05-10 20:05:17",
        "id": 9
      },
      {
        "type": "task",
        "title": "Task Overdue: Irrigation Repair",
        "message": "Samuel Kibet task \"Repair irrigation pipe — Section E-3\" is 2 hours overdue. Status still Pending.",
        "channels": [
          "in_app"
        ],
        "recipient_role": "farm_manager",
        "read": false,
        "created_at": "2026-05-10 20:05:17",
        "id": 10
      },
      {
        "type": "system",
        "title": "Daily Backup Complete",
        "message": "Automatic daily backup completed at 02:00. All farm data secured (2.4MB). Last backup: 2026-05-09 02:00.",
        "channels": [
          "in_app"
        ],
        "recipient_role": "super_admin",
        "read": true,
        "created_at": "2026-05-10 20:05:17",
        "id": 11
      },
      {
        "type": "weather",
        "title": "Frost Advisory — Next 3 Nights",
        "message": "Temperatures expected to drop to 8°C. Protect greenhouse crops and young transplants with frost covers.",
        "channels": [
          "in_app",
          "sms"
        ],
        "recipient_role": "agronomist",
        "read": true,
        "created_at": "2026-05-10 20:05:17",
        "id": 12
      },
      {
        "type": "irrigation",
        "title": "Irrigation Alert — Farm",
        "message": "Irrigation alert sent from dashboard",
        "channels": [
          "in_app",
          "sms"
        ],
        "recipient_role": "farm_manager",
        "read": false,
        "sent_channels": [],
        "id": 13,
        "created_at": "2026-05-10 20:47:54"
      },
      {
        "type": "disease",
        "title": "Disease Alert: Pathogen Detected",
        "message": "Disease alert sent from dashboard",
        "channels": [
          "in_app",
          "sms",
          "email"
        ],
        "recipient_role": "agronomist",
        "read": false,
        "sent_channels": [],
        "id": 14,
        "created_at": "2026-05-10 20:47:54"
      },
      {
        "type": "weather",
        "title": "Weather Alert: undefined",
        "message": "Weather alert sent from dashboard",
        "channels": [
          "in_app",
          "sms"
        ],
        "recipient_role": "all",
        "read": false,
        "severity": "warning",
        "sent_channels": [],
        "id": 15,
        "created_at": "2026-05-10 20:48:00"
      },
      {
        "type": "irrigation",
        "title": "Irrigation Alert — Farm",
        "message": "Irrigation alert sent from dashboard",
        "channels": [
          "in_app",
          "sms"
        ],
        "recipient_role": "farm_manager",
        "read": false,
        "sent_channels": [],
        "id": 16,
        "created_at": "2026-05-10 20:48:05"
      },
      {
        "type": "irrigation",
        "title": "Irrigation Alert — Farm",
        "message": "Irrigation alert sent from dashboard",
        "channels": [
          "in_app",
          "sms"
        ],
        "recipient_role": "farm_manager",
        "read": false,
        "sent_channels": [],
        "id": 17,
        "created_at": "2026-05-10 22:09:49"
      }
    ],
    "seq": 17
  }
}